wikijs/__init__.py
wikijs/base.py
wikijs/client.py
wikijs/regulators.py
wikijs/methods/__init__.py
wikijs/methods/analytics.py
wikijs/methods/assets.py
wikijs/methods/authentication.py
wikijs/methods/comments.py
wikijs/methods/contribute.py
wikijs/methods/groups.py
wikijs/methods/localization.py
wikijs/methods/logging.py
wikijs/methods/mail.py
wikijs/methods/navigation.py
wikijs/methods/pages.py
wikijs/methods/rendering.py
wikijs/methods/search.py
wikijs/methods/site.py
wikijs/methods/storage.py
wikijs/methods/system.py
wikijs/methods/theming.py
wikijs/methods/users.py
wikijs/schemas/__init__.py
wikijs/schemas/actions.py
wikijs/schemas/responses.py
wikijs/schemas/resources/__init__.py
wikijs/schemas/resources/analytics.py
wikijs/schemas/resources/assets.py
wikijs/schemas/resources/authentication.py
wikijs/schemas/resources/comments.py
wikijs/schemas/resources/contribute.py
wikijs/schemas/resources/groups.py
wikijs/schemas/resources/localization.py
wikijs/schemas/resources/logging.py
wikijs/schemas/resources/mail.py
wikijs/schemas/resources/navigation.py
wikijs/schemas/resources/pages.py
wikijs/schemas/resources/rendering.py
wikijs/schemas/resources/search.py
wikijs/schemas/resources/site.py
wikijs/schemas/resources/storage.py
wikijs/schemas/resources/system.py
wikijs/schemas/resources/theming.py
wikijs/schemas/resources/users.py
wikijs_pyclient-1.0.1.dist-info/LICENSE
wikijs_pyclient-1.0.1.dist-info/METADATA
wikijs_pyclient-1.0.1.dist-info/WHEEL
wikijs_pyclient-1.0.1.dist-info/top_level.txt
wikijs_pyclient-1.0.1.dist-info/RECORD
